pilli/__init__.py
pilli/__main__.py
pilli/cli.py
pilli/fields.py
pilli/pilli.py
pilli/tables.py
pilli/types.py
test/__init__.py
test/conftest.py
test/test_cli.py
test/test_fields.py
test/test_pilli.py
test/test_tables.py
test/test_types.py
pilli-2022.7.28.dist-info/LICENSE
pilli-2022.7.28.dist-info/METADATA
pilli-2022.7.28.dist-info/WHEEL
pilli-2022.7.28.dist-info/entry_points.txt
pilli-2022.7.28.dist-info/top_level.txt
pilli-2022.7.28.dist-info/RECORD
