Metadata-Version: 2.1
Name: pilli
Version: 2022.7.28
Summary: The whistle (Finnish: pilli, German: Der Pfiff) parsing random DAFIF like data.
Home-page: https://git.sr.ht/~sthagen/pilli
Author: Stefan Hagen
Author-email: stefan@hagen.link
Maintainer: Stefan Hagen
Maintainer-email: stefan@hagen.link
Project-URL: Bug Tracker, https://todo.sr.ht/~sthagen/pilli
Project-URL: Documentation, https://codes.dilettant.life/docs/pilli
Project-URL: Source Code, https://git.sr.ht/~sthagen/pilli
Project-URL: Test Coverage, https://codes.dilettant.life/coverage/pilli
Keywords: code-generation,developer-tools,validation,verification
Classifier: Development Status :: 3 - Alpha
Classifier: Intended Audience :: Developers
Classifier: License :: OSI Approved :: MIT License
Classifier: Programming Language :: Python :: 3.10
Classifier: Programming Language :: Python :: 3.8
Classifier: Programming Language :: Python :: 3.9
Requires-Python: >=3.8
License-File: LICENSE
Requires-Dist: scooby (>=0.6.0)
Requires-Dist: typer (>=0.6.1)
